opentelemetry/semconv/ai/__init__.py
opentelemetry/semconv/ai/utils.py
opentelemetry/semconv/ai/version.py
opentelemetry_if_semantic_conventions_ai-0.3.6.dist-info/METADATA
opentelemetry_if_semantic_conventions_ai-0.3.6.dist-info/WHEEL
opentelemetry_if_semantic_conventions_ai-0.3.6.dist-info/RECORD
