Metadata-Version: 2.3
Name: opentelemetry-if-semantic-conventions-ai
Version: 0.3.6
Summary: OpenTelemetry Semantic Conventions Extension for Large Language Models
License: Apache-2.0
Author: Gal Kleinman
Author-email: gal@traceloop.com
Requires-Python: >=3.9,<4
Classifier: License :: OSI Approved :: Apache Software License
Classifier: Programming Language :: Python :: 3
Classifier: Programming Language :: Python :: 3.9
Classifier: Programming Language :: Python :: 3.10
Classifier: Programming Language :: Python :: 3.11
Classifier: Programming Language :: Python :: 3.12
Classifier: Programming Language :: Python :: 3.13
